{"Level": {
  "actors": {
    "Player@6653436e": {
      "components": {
        "Rect@5eea84b9": {
          "parent": {},
          "halfW": 16,
          "h": 32,
          "edgeT": 0,
          "localPosition": {},
          "edgeR": 288,
          "edgeL": 256,
          "halfH": 16,
          "w": 32,
          "x": 272,
          "y": 16,
          "edgeB": 32,
          "id": "d8ff8457-486c-4c73-b8f4-7ed7b87097ef"
        },
        "Movement@16e69679": {
          "parent": {},
          "moveTime": "6651dc74-e237-416c-8d1a-094556380764",
          "isMoving": false,
          "moveAmount": {},
          "id": "3af07af4-2443-457c-8135-c55e59c13320",
          "newLocation": {}
        }
      },
      "m_Movement": "3af07af4-2443-457c-8135-c55e59c13320",
      "m_Rect": "d8ff8457-486c-4c73-b8f4-7ed7b87097ef",
      "location": {},
      "id": "c60aa786-a107-4989-8282-dca3d0dbe024",
      "actorState": {"ACTOR_STATE": "AWAKE"}
    },
    "Tile@47eeea5": {
      "components": {"Rect@d4fb9e3": {
        "parent": {},
        "halfW": 16,
        "h": 32,
        "edgeT": 0,
        "localPosition": {"PVector": {
          "x": 0,
          "y": 0,
          "z": 0
        }},
        "edgeR": 288,
        "edgeL": 256,
        "halfH": 16,
        "w": 32,
        "x": 272,
        "y": 16,
        "edgeB": 32,
        "id": "21d63f1f-7e63-4268-bb74-e2ac335f1255"
      }},
      "heldItem": "c60aa786-a107-4989-8282-dca3d0dbe024",
      "location": {"PVector": {
        "x": 272,
        "y": 16,
        "z": 0
      }},
      "id": "07ed8412-0c8d-472c-a439-9c1ed90af359",
      "actorState": {"ACTOR_STATE": "AWAKE"}
    }
  },
  "type": {"LEVEL_TYPE": "LEVEL"},
  "commands": {}
}}